roborcon.py
roborcon-0.5.0.dist-info/METADATA
roborcon-0.5.0.dist-info/WHEEL
roborcon-0.5.0.dist-info/top_level.txt
roborcon-0.5.0.dist-info/RECORD
