Metadata-Version: 2.1
Name: roborcon
Version: 0.5.0
Summary: A Minecraft server rcon-dependent library made only for Robocode school.
Author-email: Artem Ljukshin <garo109696@gmail.com>
Classifier: Programming Language :: Python :: 3
Classifier: License :: OSI Approved :: MIT License
Classifier: Operating System :: OS Independent
Requires-Python: >=3.8
Requires-Dist: mcrcon
Requires-Dist: requests
